README.md
comic2pdf.py
setup.py
comic2pdf.egg-info/PKG-INFO
comic2pdf.egg-info/SOURCES.txt
comic2pdf.egg-info/dependency_links.txt
comic2pdf.egg-info/entry_points.txt
comic2pdf.egg-info/requires.txt
comic2pdf.egg-info/top_level.txt
comic2pdf.egg-info/zip-safe