Metadata-Version: 2.1
Name: comic2pdf
Version: 3.0.1
Summary: Converts .cbr and .cbz files to .pdf
Home-page: http://www.phdesign.com.au/comic2pdf
Author: Paul Heasley
Author-email: paul@phdesign.com.au
License: WTFPL
Download-URL: https://github.com/phdesign/comic2pdf/archive/v3.0.1.tar.gz
Keywords: comic,pdf,cbr,cbz,convert
Platform: UNKNOWN
